{"pipelineKey":"def571e2-0869-4dd1-888e-0dc95a8dd46d","name":"Filter dataset","description":null,"definition":null,"option":null,"parameter":null,"engineDetail":null,"testcaseDetails":[{"testcaseKey":"2e175b06-43d1-45d0-943c-68eb01c5d816","objectType":"dataflow","objectKey":"15a5bd3b-5c08-486a-b0a9-da45308162f2","objectName":"Report to Data validation","parameters":"[{\"name\":\"limit_rows\",\"defValueInBatchMode\":\"limit 1000\"},{\"name\":\"insurance_claims_mart>policy_state>basic>Slicer>Slicer>c954a3b27c1075173b35\",\"defValueInBatchMode\":\"${insurance_claims_mart>policy_state>basic>Slicer>Slicer>c954a3b27c1075173b35}\"},{\"name\":\"insurance_claims_mart>incident_type>basic>Slicer>Slicer>995fa3827685b3008489\",\"defValueInBatchMode\":\"${insurance_claims_mart>incident_type>basic>Slicer>Slicer>995fa3827685b3008489}\"}]","taskType":"iteration","taskName":"Report to Data validation_iteration","additionalDetails":"{\"dynamic\":\"true\",\"dynamicIterationType\":\"FilterDataset\",\"iterationDataSetName\":\"state_and_incidenttype\",\"iterationPercentage\":100}"},{"testcaseKey":"a1ca257b-6e74-4205-97c9-78924abd893e","objectType":"dataflow","objectKey":"65864456-c7b7-4159-8d8e-8e5602d5e086","objectName":"Report to Report Tableau","parameters":"[{\"name\":\"limit_rows\",\"defValueInBatchMode\":\"limit 1000\",\"type\":\"static\"}]","taskType":"normal","taskName":"Report to Report Tableau","additionalDetails":null},{"testcaseKey":"2215133b-103d-4db0-9c4a-10a9a6042c78","objectType":"dataflow","objectKey":"8f522768-313d-4f69-85ab-e6462444cc36","objectName":"DIRECT_MAPPING_INSURANCE_CLAIMS_STG_TO_INSURANCE_CLAIMS_MART_ALL_COLUMNS","parameters":"[{\"name\":\"limit_rows\",\"defValueInBatchMode\":\"limit 10\"}]","taskType":"normal","taskName":"DIRECT_MAPPING_INSURANCE_CLAIMS_STG_TO_INSURANCE_CLAIMS_MART_ALL_COLUMNS","additionalDetails":null},{"testcaseKey":"645315de-4a41-404f-be11-b523ccf0d6d8","objectType":"dataflow","objectKey":"88ea0e9d-8919-4144-aed4-ad5579b8cc69","objectName":"EXPRESSION_PREMIUM_BUCKET_HIGH_RISK_FLAG_CUSTOMER_TENURE_CAT_CLAIM_SEVERITY_SCORE_AGE_GROUP_TOTAL_CL","parameters":"[{\"name\":\"limit_rows\",\"defValueInBatchMode\":\"limit 10\"}]","taskType":"normal","taskName":"EXPRESSION_PREMIUM_BUCKET_HIGH_RISK_FLAG_CUSTOMER_TENURE_CAT_CLAIM_SEVERITY_SCORE_AGE_GROUP_TOTAL_CL","additionalDetails":null}],"pipelineType":"noDependency"}