{"name":"insurance_claims_mart","description":null,"dataSourceName":"Snowflake","tableDataModels":[{"tableName":"INSURANCE_CLAIMS_MART","schemaName":"DGPOC.POC","description":null,"columns":[{"columnName":"SNO","description":"","dataType":"NUMBER","isNull":"Y","attributeName":null,"entityName":null,"columnOrder":1,"columnLength":null,"columnAlias":null,"additionalInfo":null},{"columnName":"MONTHS_AS_CUSTOMER","description":"","dataType":"NUMBER","isNull":"Y","attributeName":null,"entityName":null,"columnOrder":2,"columnLength":null,"columnAlias":null,"additionalInfo":null},{"columnName":"AGE","description":"","dataType":"NUMBER","isNull":"Y","attributeName":null,"entityName":null,"columnOrder":3,"columnLength":null,"columnAlias":null,"additionalInfo":null},{"columnName":"POLICY_NUMBER","description":"","dataType":"NUMBER","isNull":"Y","attributeName":null,"entityName":null,"columnOrder":4,"columnLength":null,"columnAlias":null,"additionalInfo":null},{"columnName":"POLICY_STATE","description":"","dataType":"TEXT","isNull":"Y","attributeName":null,"entityName":null,"columnOrder":5,"columnLength":"16777216","columnAlias":null,"additionalInfo":null},{"columnName":"POLICY_CSL","description":"","dataType":"TEXT","isNull":"Y","attributeName":null,"entityName":null,"columnOrder":6,"columnLength":"16777216","columnAlias":null,"additionalInfo":null},{"columnName":"POLICY_DEDUCTABLE","description":"","dataType":"NUMBER","isNull":"Y","attributeName":null,"entityName":null,"columnOrder":7,"columnLength":null,"columnAlias":null,"additionalInfo":null},{"columnName":"POLICY_ANNUAL_PREMIUM","description":"","dataType":"NUMBER","isNull":"Y","attributeName":null,"entityName":null,"columnOrder":8,"columnLength":null,"columnAlias":null,"additionalInfo":null},{"columnName":"UMBRELLA_LIMIT","description":"","dataType":"NUMBER","isNull":"Y","attributeName":null,"entityName":null,"columnOrder":9,"columnLength":null,"columnAlias":null,"additionalInfo":null},{"columnName":"INSURED_ZIP","description":"","dataType":"NUMBER","isNull":"Y","attributeName":null,"entityName":null,"columnOrder":10,"columnLength":null,"columnAlias":null,"additionalInfo":null},{"columnName":"INSURED_SEX","description":"","dataType":"TEXT","isNull":"Y","attributeName":null,"entityName":null,"columnOrder":11,"columnLength":"16777216","columnAlias":null,"additionalInfo":null},{"columnName":"INSURED_EDUCATION_LEVEL","description":"","dataType":"TEXT","isNull":"Y","attributeName":null,"entityName":null,"columnOrder":12,"columnLength":"16777216","columnAlias":null,"additionalInfo":null},{"columnName":"INSURED_OCCUPATION","description":"","dataType":"TEXT","isNull":"Y","attributeName":null,"entityName":null,"columnOrder":13,"columnLength":"16777216","columnAlias":null,"additionalInfo":null},{"columnName":"INSURED_HOBBIES","description":"","dataType":"TEXT","isNull":"Y","attributeName":null,"entityName":null,"columnOrder":14,"columnLength":"16777216","columnAlias":null,"additionalInfo":null},{"columnName":"INSURED_RELATIONSHIP","description":"","dataType":"TEXT","isNull":"Y","attributeName":null,"entityName":null,"columnOrder":15,"columnLength":"16777216","columnAlias":null,"additionalInfo":null},{"columnName":"CAPITAL_GAINS","description":"","dataType":"NUMBER","isNull":"Y","attributeName":null,"entityName":null,"columnOrder":16,"columnLength":null,"columnAlias":null,"additionalInfo":null},{"columnName":"CAPITAL_LOSS","description":"","dataType":"NUMBER","isNull":"Y","attributeName":null,"entityName":null,"columnOrder":17,"columnLength":null,"columnAlias":null,"additionalInfo":null},{"columnName":"INCIDENT_DATE","description":"","dataType":"TEXT","isNull":"Y","attributeName":null,"entityName":null,"columnOrder":18,"columnLength":"16777216","columnAlias":null,"additionalInfo":null},{"columnName":"INCIDENT_TYPE","description":"","dataType":"TEXT","isNull":"Y","attributeName":null,"entityName":null,"columnOrder":19,"columnLength":"16777216","columnAlias":null,"additionalInfo":null},{"columnName":"COLLISION_TYPE","description":"","dataType":"TEXT","isNull":"Y","attributeName":null,"entityName":null,"columnOrder":20,"columnLength":"16777216","columnAlias":null,"additionalInfo":null},{"columnName":"INCIDENT_SEVERITY","description":"","dataType":"TEXT","isNull":"Y","attributeName":null,"entityName":null,"columnOrder":21,"columnLength":"16777216","columnAlias":null,"additionalInfo":null},{"columnName":"AUTHORITIES_CONTACTED","description":"","dataType":"TEXT","isNull":"Y","attributeName":null,"entityName":null,"columnOrder":22,"columnLength":"16777216","columnAlias":null,"additionalInfo":null},{"columnName":"INCIDENT_STATE","description":"","dataType":"TEXT","isNull":"Y","attributeName":null,"entityName":null,"columnOrder":23,"columnLength":"16777216","columnAlias":null,"additionalInfo":null},{"columnName":"INCIDENT_CITY","description":"","dataType":"TEXT","isNull":"Y","attributeName":null,"entityName":null,"columnOrder":24,"columnLength":"16777216","columnAlias":null,"additionalInfo":null},{"columnName":"INCIDENT_LOCATION","description":"","dataType":"TEXT","isNull":"Y","attributeName":null,"entityName":null,"columnOrder":25,"columnLength":"16777216","columnAlias":null,"additionalInfo":null},{"columnName":"INCIDENT_HOUR_OF_THE_DAY","description":"","dataType":"NUMBER","isNull":"Y","attributeName":null,"entityName":null,"columnOrder":26,"columnLength":null,"columnAlias":null,"additionalInfo":null},{"columnName":"NUMBER_OF_VEHICLES_INVOLVED","description":"","dataType":"NUMBER","isNull":"Y","attributeName":null,"entityName":null,"columnOrder":27,"columnLength":null,"columnAlias":null,"additionalInfo":null},{"columnName":"PROPERTY_DAMAGE","description":"","dataType":"TEXT","isNull":"Y","attributeName":null,"entityName":null,"columnOrder":28,"columnLength":"16777216","columnAlias":null,"additionalInfo":null},{"columnName":"BODILY_INJURIES","description":"","dataType":"NUMBER","isNull":"Y","attributeName":null,"entityName":null,"columnOrder":29,"columnLength":null,"columnAlias":null,"additionalInfo":null},{"columnName":"WITNESSES","description":"","dataType":"NUMBER","isNull":"Y","attributeName":null,"entityName":null,"columnOrder":30,"columnLength":null,"columnAlias":null,"additionalInfo":null},{"columnName":"POLICE_REPORT_AVAILABLE","description":"","dataType":"TEXT","isNull":"Y","attributeName":null,"entityName":null,"columnOrder":31,"columnLength":"16777216","columnAlias":null,"additionalInfo":null},{"columnName":"TOTAL_CLAIM_AMOUNT","description":"","dataType":"NUMBER","isNull":"Y","attributeName":null,"entityName":null,"columnOrder":32,"columnLength":null,"columnAlias":null,"additionalInfo":null},{"columnName":"INJURY_CLAIM","description":"","dataType":"NUMBER","isNull":"Y","attributeName":null,"entityName":null,"columnOrder":33,"columnLength":null,"columnAlias":null,"additionalInfo":null},{"columnName":"PROPERTY_CLAIM","description":"","dataType":"NUMBER","isNull":"Y","attributeName":null,"entityName":null,"columnOrder":34,"columnLength":null,"columnAlias":null,"additionalInfo":null},{"columnName":"VEHICLE_CLAIM","description":"","dataType":"NUMBER","isNull":"Y","attributeName":null,"entityName":null,"columnOrder":35,"columnLength":null,"columnAlias":null,"additionalInfo":null},{"columnName":"AUTO_MAKE","description":"","dataType":"TEXT","isNull":"Y","attributeName":null,"entityName":null,"columnOrder":36,"columnLength":"16777216","columnAlias":null,"additionalInfo":null},{"columnName":"AUTO_MODEL","description":"","dataType":"TEXT","isNull":"Y","attributeName":null,"entityName":null,"columnOrder":37,"columnLength":"16777216","columnAlias":null,"additionalInfo":null},{"columnName":"AUTO_YEAR","description":"","dataType":"NUMBER","isNull":"Y","attributeName":null,"entityName":null,"columnOrder":38,"columnLength":null,"columnAlias":null,"additionalInfo":null},{"columnName":"FRAUD_REPORTED","description":"","dataType":"TEXT","isNull":"Y","attributeName":null,"entityName":null,"columnOrder":39,"columnLength":"16777216","columnAlias":null,"additionalInfo":null},{"columnName":"AGE_GROUP","description":"","dataType":"TEXT","isNull":"Y","attributeName":null,"entityName":null,"columnOrder":40,"columnLength":"16777216","columnAlias":null,"additionalInfo":null},{"columnName":"PREMIUM_BUCKET","description":"","dataType":"TEXT","isNull":"Y","attributeName":null,"entityName":null,"columnOrder":41,"columnLength":"16777216","columnAlias":null,"additionalInfo":null},{"columnName":"CUSTOMER_TENURE_CAT","description":"","dataType":"TEXT","isNull":"Y","attributeName":null,"entityName":null,"columnOrder":42,"columnLength":"16777216","columnAlias":null,"additionalInfo":null},{"columnName":"CLAIM_SEVERITY_SCORE","description":"","dataType":"NUMBER","isNull":"Y","attributeName":null,"entityName":null,"columnOrder":43,"columnLength":null,"columnAlias":null,"additionalInfo":null},{"columnName":"TOTAL_CLAIM_VERIFIED","description":"","dataType":"NUMBER","isNull":"Y","attributeName":null,"entityName":null,"columnOrder":44,"columnLength":null,"columnAlias":null,"additionalInfo":null},{"columnName":"HIGH_RISK_FLAG","description":"","dataType":"NUMBER","isNull":"Y","attributeName":null,"entityName":null,"columnOrder":45,"columnLength":null,"columnAlias":null,"additionalInfo":null}],"rules":[],"relations":null,"sdvTemplate":null,"sampleDataSettingsJson":null,"datasourceName":"Snowflake","datasourceType":"Snowflake","uniqueColumns":null,"tagNames":[]}],"workschemaName":null,"dmkey":"6edf4697-2677-479d-b761-e5aa8b4809a4","type":null,"additionalInfo":{"catalogName":null},"tableGroups":[{"groupName":"default","groupDescription":"Default table group","parallelRuns":5,"sampleResultCount":10,"workSchemaTrackingName":null,"failureFileLocation":null,"maxFailureRecords":0,"tables":[],"profileOptions":""}],"schemaMappings":null}